httpie_websockets-1.0.0.dist-info/METADATA
httpie_websockets-1.0.0.dist-info/WHEEL
httpie_websockets-1.0.0.dist-info/entry_points.txt
httpie_websockets-1.0.0.dist-info/licenses/LICENSE
httpie_websockets.py
httpie_websockets-1.0.0.dist-info/RECORD
