Metadata-Version: 2.1
Name: httpie-websockets
Version: 1.0.0
Summary: Websocket plugin for httpie
Keywords: http,httpie,plugin,websocket,websockets
Author-Email: belingud <1170202353@qq.com>
License: MIT License
Classifier: Programming Language :: Python :: 3.8
Classifier: Programming Language :: Python :: 3.9
Classifier: Programming Language :: Python :: 3.10
Classifier: Programming Language :: Python :: 3.11
Classifier: Programming Language :: Python :: 3.12
Classifier: License :: OSI Approved :: MIT License
Classifier: Environment :: Console
Classifier: Operating System :: OS Independent
Classifier: Intended Audience :: Developers
Classifier: Intended Audience :: System Administrators
Classifier: Topic :: Internet :: WWW/HTTP
Classifier: Topic :: Software Development
Classifier: Topic :: System :: Networking
Classifier: Topic :: Terminals
Classifier: Topic :: Text Processing
Classifier: Topic :: Utilities
Project-URL: Homepage, https://github.com/belingud/httpie-websockets
Project-URL: Documentation, https://github.com/belingud/httpie-websockets
Project-URL: Issues, https://github.com/belingud/httpie-websockets/issues
Project-URL: Source, https://github.com/belingud/httpie-websockets
Project-URL: Github, https://github.com/belingud/httpie-websockets
Requires-Python: >=3.8
Requires-Dist: requests>=2.31.0
Requires-Dist: httpie>=3.2.3
Requires-Dist: websocket-client>=1.8.0
Requires-Dist: python-socks>=2.5.0
